[
    {
        "internalName": "AnonymousPlugin",
        "name": "Anonymous Mode",
        "description": "Hide your in-game identity.",
        "tags": [
            "chat",
            "mask",
            "hide",
            "anonymous"
        ],
        "version": "1.0.0",
        "minClientVersion": "1.9.6",
        "author": "Bolado",
        "supportUrl": "https://github.com/chsami/microbot",
        "iconUrl": "https://oldschool.runescape.wiki/images/Rogue_mask_chathead.png?0b359",
        "sha256": "7563e0e4ded82d77a553a2f02e71ecd648e2a0feadbe880a4b285e224ebc4c38",
        "url": "https://nexus.microbot.cloud/repository/microbot-plugins/net/runelite/client/plugins/microbot/anonymousplugin/1.0.0/anonymousplugin-1.0.0.jar"
    },
    {
        "internalName": "BlessedWinePlugin",
        "name": "Blessed Wine",
        "description": "Automating Prayer Training using blessed wines at Cam Torum",
        "tags": [
            "blessed",
            "wine",
            "ralos",
            "prayer",
            "libation",
            "microbot",
            "automation"
        ],
        "version": "1.0.0",
        "minClientVersion": "1.9.6",
        "author": "Hal",
        "supportUrl": "https://github.com/chsami/microbot",
        "iconUrl": "https://oldschool.runescape.wiki/images/Jug_of_wine.png",
        "sha256": "6b801c23da7a52bc8dcfdfdba7f6d98e46a05b8c2751607173a30ecfe4395a4c",
        "url": "https://nexus.microbot.cloud/repository/microbot-plugins/net/runelite/client/plugins/microbot/blessedwineplugin/1.0.0/blessedwineplugin-1.0.0.jar"
    },
    {
        "internalName": "PestControlPlugin",
        "name": "Pest Control",
        "description": "Supports all boats, portals, and shields.",
        "tags": [
            "pest control",
            "microbot",
            "minigames"
        ],
        "version": "2.2.4",
        "minClientVersion": "1.9.6",
        "author": "Mocrosoft",
        "supportUrl": "https://github.com/chsami/microbot",
        "iconUrl": "https://oldschool.runescape.wiki/images/Pest_Control.png?ed7bb",
        "sha256": "647781a86c0df26881c846d52cd601a0991113e6c5cb9453e6693d8b73f57d70",
        "url": "https://nexus.microbot.cloud/repository/microbot-plugins/net/runelite/client/plugins/microbot/pestcontrolplugin/2.2.4/pestcontrolplugin-2.2.4.jar"
    }
]